readchar/__init__.py
readchar/_base_key.py
readchar/_config.py
readchar/_posix_key.py
readchar/_posix_read.py
readchar/_win_key.py
readchar/_win_read.py
readchar/key.py
readchar/py.typed
readchar-4.0.6.dist-info/LICENCE
readchar-4.0.6.dist-info/METADATA
readchar-4.0.6.dist-info/WHEEL
readchar-4.0.6.dist-info/top_level.txt
readchar-4.0.6.dist-info/RECORD
