Metadata-Version: 2.1
Name: readchar
Version: 4.0.6
Summary: Library to easily read single chars and key strokes
Home-page: https://github.com/magmax/python-readchar
Author: Miguel Ángel García
Author-email: miguelangel.garcia@gmail.com
License: MIT
Project-URL: Download, https://pypi.org/project/readchar/#files
Project-URL: Bug Tracker, https://github.com/magmax/python-readchar/issues
Project-URL: Source Code, https://github.com/magmax/python-readchar
Keywords: characters,keystrokes,stdin,command line
Classifier: Development Status :: 5 - Production/Stable
Classifier: Environment :: Console
Classifier: Intended Audience :: Developers
Classifier: License :: OSI Approved :: MIT License
Classifier: Operating System :: Microsoft :: Windows
Classifier: Operating System :: POSIX :: Linux
Classifier: Programming Language :: Python :: 3
Classifier: Programming Language :: Python :: 3 :: Only
Classifier: Programming Language :: Python :: 3.8
Classifier: Programming Language :: Python :: 3.9
Classifier: Programming Language :: Python :: 3.10
Classifier: Programming Language :: Python :: 3.11
Classifier: Programming Language :: Python :: 3.12
Classifier: Programming Language :: Python :: Implementation :: CPython
Classifier: Topic :: Software Development
Classifier: Topic :: Software Development :: User Interfaces
Requires-Python: >=3.8
License-File: LICENCE
Requires-Dist: setuptools>=41.0
